{
  "status": "PASS",
  "next_stage": "06_document",
  "human_gate_required": false,
  "blocking_reason": "",
  "history_notes": {
    "implemented": [
      "FastAPI 백엔드 서비스 구현 및 Stooq, Frankfurter 어댑터 연동",
      "React/Vite/TypeScript 프론트엔드 다크 테마 대시보드 UI 구현",
      "Windows 배치파일 (start-dashboard.bat, stop-dashboard.bat) 구현 및 PID 기반 프로세스 라이프사이클 관리",
      "백엔드 30초 TTL 인메모리 캐싱 및 stale 캐시 fallback 기능 구현",
      "외부 API 호출 장애 시 예외 격리(try-except 안전망) 적용 및 테스트 통과"
    ],
    "risks": [
      "무료 API(Stooq, Frankfurter)의 순간적인 Rate Limit 및 응답 불안정성",
      "Windows 환경에서 포트 충돌 가능성 (start-dashboard.bat에서 포트 검증으로 완화)"
    ],
    "future_improvements": [
      "프로세스 메모리 기반 캐시를 Redis 등으로 마이그레이션",
      "Frankfurter fallback 외의 추가적인 무료 환율 데이터 소스 확보"
    ],
    "decisions": [
      "무료·무인증 Stooq CSV 및 Frankfurter API를 핵심 공급자로 선정",
      "Windows 배치파일을 제공하되, 백그라운드 구동 후 PID로 추적하여 안전 종료 처리",
      "하네스의 non-interactive 특성을 고려하여 배치파일 차단 오류 시 pause 명령 제외"
    ],
    "unresolved_items": []
  },
  "test_commands": [
    {
      "name": "backend_tests",
      "command": [
        "python",
        "-m",
        "pytest",
        "tests/backend",
        "tests/scripts",
        "-p",
        "no:cacheprovider"
      ],
      "cwd": ".",
      "timeout_seconds": 600,
      "persist": true
    },
    {
      "name": "frontend_tests",
      "command": [
        "npm.cmd",
        "test"
      ],
      "cwd": "src/frontend",
      "timeout_seconds": 600,
      "persist": true
    },
    {
      "name": "frontend_build",
      "command": [
        "npm.cmd",
        "run",
        "build"
      ],
      "cwd": "src/frontend",
      "timeout_seconds": 600,
      "persist": true
    }
  ]
}
